{"meta":{"version":1,"warehouse":"4.0.2"},"models":{"Asset":[{"_id":"themes/tkl/source/css/all.styl","path":"css/all.styl","modified":0,"renderable":1},{"_id":"themes/tkl/source/css/animate.css","path":"css/animate.css","modified":0,"renderable":1},{"_id":"themes/tkl/source/css/bootstrap.min.css","path":"css/bootstrap.min.css","modified":0,"renderable":1},{"_id":"themes/tkl/source/css/custom.css","path":"css/custom.css","modified":0,"renderable":1},{"_id":"themes/tkl/source/css/animsition.min.css","path":"css/animsition.min.css","modified":0,"renderable":1},{"_id":"themes/tkl/source/css/iconList.css","path":"css/iconList.css","modified":0,"renderable":1},{"_id":"themes/tkl/source/css/flexslider.css","path":"css/flexslider.css","modified":0,"renderable":1},{"_id":"themes/tkl/source/css/ie8.css","path":"css/ie8.css","modified":0,"renderable":1},{"_id":"themes/tkl/source/css/screen.css","path":"css/screen.css","modified":0,"renderable":1},{"_id":"themes/tkl/source/css/slidebars.min.css","path":"css/slidebars.min.css","modified":0,"renderable":1},{"_id":"themes/tkl/source/css/syntax.styl","path":"css/syntax.styl","modified":0,"renderable":1},{"_id":"themes/tkl/source/css/style.css","path":"css/style.css","modified":0,"renderable":1},{"_id":"themes/tkl/source/fancybox/fancybox_loading.gif","path":"fancybox/fancybox_loading.gif","modified":0,"renderable":1},{"_id":"themes/tkl/source/fancybox/fancybox_loading@2x.gif","path":"fancybox/fancybox_loading@2x.gif","modified":0,"renderable":1},{"_id":"themes/tkl/source/fancybox/blank.gif","path":"fancybox/blank.gif","modified":0,"renderable":1},{"_id":"themes/tkl/source/fancybox/fancybox_overlay.png","path":"fancybox/fancybox_overlay.png","modified":0,"renderable":1},{"_id":"themes/tkl/source/fancybox/fancybox_sprite@2x.png","path":"fancybox/fancybox_sprite@2x.png","modified":0,"renderable":1},{"_id":"themes/tkl/source/fancybox/fancybox_sprite.png","path":"fancybox/fancybox_sprite.png","modified":0,"renderable":1},{"_id":"themes/tkl/source/fancybox/jquery.fancybox.css","path":"fancybox/jquery.fancybox.css","modified":0,"renderable":1},{"_id":"themes/tkl/source/fonts/icons.eot","path":"fonts/icons.eot","modified":0,"renderable":1},{"_id":"themes/tkl/source/fancybox/jquery.fancybox.pack.js","path":"fancybox/jquery.fancybox.pack.js","modified":0,"renderable":1},{"_id":"themes/tkl/source/fonts/icons.svg","path":"fonts/icons.svg","modified":0,"renderable":1},{"_id":"themes/tkl/source/fonts/icons.woff","path":"fonts/icons.woff","modified":0,"renderable":1},{"_id":"themes/tkl/source/fonts/icons.ttf","path":"fonts/icons.ttf","modified":0,"renderable":1},{"_id":"themes/tkl/source/fonts/opensans.woff","path":"fonts/opensans.woff","modified":0,"renderable":1},{"_id":"themes/tkl/source/img/1326 - Ring.ico","path":"img/1326 - Ring.ico","modified":0,"renderable":1},{"_id":"themes/tkl/source/img/1326 - Ring.png","path":"img/1326 - Ring.png","modified":0,"renderable":1},{"_id":"themes/tkl/source/img/banner-1033925_640.jpg","path":"img/banner-1033925_640.jpg","modified":0,"renderable":1},{"_id":"themes/tkl/source/img/close.png","path":"img/close.png","modified":0,"renderable":1},{"_id":"themes/tkl/source/img/favicon.ico","path":"img/favicon.ico","modified":0,"renderable":1},{"_id":"themes/tkl/source/js/jquery-1.11.1.min.js","path":"js/jquery-1.11.1.min.js","modified":0,"renderable":1},{"_id":"themes/tkl/source/js/html5shiv.min.js","path":"js/html5shiv.min.js","modified":0,"renderable":1},{"_id":"themes/tkl/source/js/jquery.ajaxchimp.min.js","path":"js/jquery.ajaxchimp.min.js","modified":0,"renderable":1},{"_id":"themes/tkl/source/js/jquery.flexslider-min.js","path":"js/jquery.flexslider-min.js","modified":0,"renderable":1},{"_id":"themes/tkl/source/js/plugins.min.js","path":"js/plugins.min.js","modified":0,"renderable":1},{"_id":"themes/tkl/source/js/respond.min.js","path":"js/respond.min.js","modified":0,"renderable":1},{"_id":"themes/tkl/source/js/scripts.js","path":"js/scripts.js","modified":0,"renderable":1},{"_id":"themes/tkl/source/js/ziploader.js","path":"js/ziploader.js","modified":0,"renderable":1},{"_id":"themes/tkl/source/highlightjs/arta.css","path":"highlightjs/arta.css","modified":0,"renderable":1},{"_id":"themes/tkl/source/highlightjs/ascetic.css","path":"highlightjs/ascetic.css","modified":0,"renderable":1},{"_id":"themes/tkl/source/highlightjs/brown_papersq.png","path":"highlightjs/brown_papersq.png","modified":0,"renderable":1},{"_id":"themes/tkl/source/highlightjs/brown_paper.css","path":"highlightjs/brown_paper.css","modified":0,"renderable":1},{"_id":"themes/tkl/source/highlightjs/dark.css","path":"highlightjs/dark.css","modified":0,"renderable":1},{"_id":"themes/tkl/source/highlightjs/default.css","path":"highlightjs/default.css","modified":0,"renderable":1},{"_id":"themes/tkl/source/highlightjs/docco.css","path":"highlightjs/docco.css","modified":0,"renderable":1},{"_id":"themes/tkl/source/highlightjs/foundation.css","path":"highlightjs/foundation.css","modified":0,"renderable":1},{"_id":"themes/tkl/source/highlightjs/far.css","path":"highlightjs/far.css","modified":0,"renderable":1},{"_id":"themes/tkl/source/highlightjs/googlecode.css","path":"highlightjs/googlecode.css","modified":0,"renderable":1},{"_id":"themes/tkl/source/highlightjs/github.css","path":"highlightjs/github.css","modified":0,"renderable":1},{"_id":"themes/tkl/source/highlightjs/idea.css","path":"highlightjs/idea.css","modified":0,"renderable":1},{"_id":"themes/tkl/source/highlightjs/ir_black.css","path":"highlightjs/ir_black.css","modified":0,"renderable":1},{"_id":"themes/tkl/source/highlightjs/magula.css","path":"highlightjs/magula.css","modified":0,"renderable":1},{"_id":"themes/tkl/source/highlightjs/mono-blue.css","path":"highlightjs/mono-blue.css","modified":0,"renderable":1},{"_id":"themes/tkl/source/highlightjs/monokai.css","path":"highlightjs/monokai.css","modified":0,"renderable":1},{"_id":"themes/tkl/source/highlightjs/obsidian.css","path":"highlightjs/obsidian.css","modified":0,"renderable":1},{"_id":"themes/tkl/source/highlightjs/monokai_sublime.css","path":"highlightjs/monokai_sublime.css","modified":0,"renderable":1},{"_id":"themes/tkl/source/highlightjs/pojoaque.jpg","path":"highlightjs/pojoaque.jpg","modified":0,"renderable":1},{"_id":"themes/tkl/source/highlightjs/railscasts.css","path":"highlightjs/railscasts.css","modified":0,"renderable":1},{"_id":"themes/tkl/source/highlightjs/rainbow.css","path":"highlightjs/rainbow.css","modified":0,"renderable":1},{"_id":"themes/tkl/source/highlightjs/pojoaque.css","path":"highlightjs/pojoaque.css","modified":0,"renderable":1},{"_id":"themes/tkl/source/highlightjs/school_book.css","path":"highlightjs/school_book.css","modified":0,"renderable":1},{"_id":"themes/tkl/source/highlightjs/school_book.png","path":"highlightjs/school_book.png","modified":0,"renderable":1},{"_id":"themes/tkl/source/highlightjs/solarized_dark.css","path":"highlightjs/solarized_dark.css","modified":0,"renderable":1},{"_id":"themes/tkl/source/highlightjs/tomorrow-night-blue.css","path":"highlightjs/tomorrow-night-blue.css","modified":0,"renderable":1},{"_id":"themes/tkl/source/highlightjs/solarized_light.css","path":"highlightjs/solarized_light.css","modified":0,"renderable":1},{"_id":"themes/tkl/source/highlightjs/sunburst.css","path":"highlightjs/sunburst.css","modified":0,"renderable":1},{"_id":"themes/tkl/source/highlightjs/tomorrow-night-bright.css","path":"highlightjs/tomorrow-night-bright.css","modified":0,"renderable":1},{"_id":"themes/tkl/source/highlightjs/tomorrow-night-eighties.css","path":"highlightjs/tomorrow-night-eighties.css","modified":0,"renderable":1},{"_id":"themes/tkl/source/highlightjs/tomorrow-night.css","path":"highlightjs/tomorrow-night.css","modified":0,"renderable":1},{"_id":"themes/tkl/source/highlightjs/tomorrow.css","path":"highlightjs/tomorrow.css","modified":0,"renderable":1},{"_id":"themes/tkl/source/highlightjs/vs.css","path":"highlightjs/vs.css","modified":0,"renderable":1},{"_id":"themes/tkl/source/highlightjs/xcode.css","path":"highlightjs/xcode.css","modified":0,"renderable":1},{"_id":"themes/tkl/source/highlightjs/zenburn.css","path":"highlightjs/zenburn.css","modified":0,"renderable":1}],"Cache":[{"_id":"source/tags/index.md","hash":"c601a9eaa56efc9b1a07b920e56b4c4837a45e78","modified":1660649775503},{"_id":"source/categories/index.md","hash":"cad4ab508764cf5c6cc08d657f575fd047275f08","modified":1660649774106},{"_id":"source/_posts/What-are-the-five-benefits-of-drinking-water-with-thermos-cup.md","hash":"8aba562de01caec7b70fadcc8b5f448926613b37","modified":1660649789881},{"_id":"themes/tkl/README.md","hash":"be19038e1bde09ad060e20b645e4d22df37eec1d","modified":1650768698000},{"_id":"themes/tkl/LICENSE","hash":"c700a8b9312d24bdc57570f7d6a131cf63d89016","modified":1650768698000},{"_id":"themes/tkl/layout/archive.ejs","hash":"a18842e3d719fe3ca9b977a6995f8facc75c8673","modified":1650768698000},{"_id":"themes/tkl/custom.json","hash":"753487dd9d66f127038655443e120ec07d49b0cd","modified":1660299250000},{"_id":"themes/tkl/_config.yml","hash":"cef26bd4bfd98376a95cc10fdc3deb8dd21a5106","modified":1663572141286},{"_id":"themes/tkl/layout/layout.ejs","hash":"bf860625a18dd23d4e7064a80e3df0f19d9784ad","modified":1650768698000},{"_id":"themes/tkl/layout/category.ejs","hash":"9b740fc33f6f028df60f0bc4312bf3ebd03aa8ea","modified":1650768698000},{"_id":"themes/tkl/layout/index.ejs","hash":"36e89b37f520533bef85fb32b714214257fad1d0","modified":1650768698000},{"_id":"themes/tkl/layout/page.ejs","hash":"29cf5f3bb27821cec6dd59d90ca1604b32f8fc0c","modified":1650768698000},{"_id":"themes/tkl/layout/tag.ejs","hash":"45150a2365768b6b67880193c9264ad2bb4814db","modified":1650768698000},{"_id":"themes/tkl/layout/post.ejs","hash":"ae761feddc98f4d3260e7591ed9fc91d9a49d0ab","modified":1650768698000},{"_id":"themes/tkl/layout/_partial/about.ejs","hash":"b0127ff072ce3158cc59301da9322c7dd9fd3a7d","modified":1650768698000},{"_id":"themes/tkl/layout/_partial/head.ejs","hash":"a3df7f3635b130c29da429dbd450848fbb59e542","modified":1660299634000},{"_id":"themes/tkl/layout/_partial/after_all.ejs","hash":"706f9dd71442877349b53d360d42eb68cbb4856f","modified":1650768698000},{"_id":"themes/tkl/layout/_partial/footer.ejs","hash":"e19d4ed9e94c73bf113663ef69d7d57671b59241","modified":1663643655604},{"_id":"themes/tkl/layout/_partial/archive.ejs","hash":"be083c1c5f865f64efbf9a17b34e5ccbe0bb9d64","modified":1650768698000},{"_id":"themes/tkl/layout/_partial/header.ejs","hash":"50bbe660ba2bf5dc0eb2b2c557fd3b80f5fd326b","modified":1660294250000},{"_id":"themes/tkl/layout/_partial/post.ejs","hash":"049c265fa02f69303f48753ae342ec2f65b9bb92","modified":1650768698000},{"_id":"themes/tkl/layout/_partial/index.ejs","hash":"461d0772d383da6c6e3ed88e93f399f02002121a","modified":1650768698000},{"_id":"themes/tkl/source/css/all.styl","hash":"9fa61a7eda4ea10ac7aac6ac438de96c3be3c487","modified":1650768698000},{"_id":"themes/tkl/layout/_partial/search.ejs","hash":"e6be2c6ef3b4d560c2b6291630e6ae1e6674c1bc","modified":1650768698000},{"_id":"themes/tkl/source/css/custom.css","hash":"e87423888bf9a13ee0bc28a5aa725f40f999608a","modified":1650768698000},{"_id":"themes/tkl/source/css/animate.css","hash":"fca75b84887199a0ed8e0f056ff30f5a1302f324","modified":1650768698000},{"_id":"themes/tkl/source/css/animsition.min.css","hash":"59033074f6594a0d87c759e2b8cf9baa3a62ed6a","modified":1650768698000},{"_id":"themes/tkl/source/css/iconList.css","hash":"f78ffffb4be40a6b0eb6ee109c958ccd062d1ae5","modified":1650768698000},{"_id":"themes/tkl/source/css/flexslider.css","hash":"faebc8c54ca41e3c9936edaffbabbebd512c6d5a","modified":1650768698000},{"_id":"themes/tkl/source/css/screen.css","hash":"a13c2c6fe420f76083df2da6d7b2d765dd8b467e","modified":1650768698000},{"_id":"themes/tkl/source/css/ie8.css","hash":"cfdfe07ecc9f3afa5bab47155b49f0924f62d2c2","modified":1650768698000},{"_id":"themes/tkl/source/css/slidebars.min.css","hash":"a802c15d9bf06005b463901be8325d8ce38b5b04","modified":1650768698000},{"_id":"themes/tkl/source/fancybox/fancybox_loading.gif","hash":"1a755fb2599f3a313cc6cfdb14df043f8c14a99c","modified":1650768698000},{"_id":"themes/tkl/source/css/syntax.styl","hash":"f39ea1e483c9244f39003d3efd20deb535ecddc7","modified":1650768698000},{"_id":"themes/tkl/source/fancybox/fancybox_loading@2x.gif","hash":"273b123496a42ba45c3416adb027cd99745058b0","modified":1650768698000},{"_id":"themes/tkl/source/fancybox/fancybox_overlay.png","hash":"b3a4ee645ba494f52840ef8412015ba0f465dbe0","modified":1650768698000},{"_id":"themes/tkl/source/fancybox/blank.gif","hash":"2daeaa8b5f19f0bc209d976c02bd6acb51b00b0a","modified":1650768698000},{"_id":"themes/tkl/source/fancybox/fancybox_sprite.png","hash":"17df19f97628e77be09c352bf27425faea248251","modified":1650768698000},{"_id":"themes/tkl/source/fancybox/fancybox_sprite@2x.png","hash":"30c58913f327e28f466a00f4c1ac8001b560aed8","modified":1650768698000},{"_id":"themes/tkl/source/fonts/icons.eot","hash":"e307fc2d61d13bbc3aafc9abd75e727cbebadee1","modified":1650768698000},{"_id":"themes/tkl/source/fancybox/jquery.fancybox.pack.js","hash":"53360764b429c212f424399384417ccc233bb3be","modified":1650768698000},{"_id":"themes/tkl/source/fancybox/jquery.fancybox.css","hash":"5f163444617b6cf267342f06ac166a237bb62df9","modified":1650768698000},{"_id":"themes/tkl/source/fonts/icons.woff","hash":"af538de6ac19d5da1cada203c7451ce32f5daceb","modified":1650768698000},{"_id":"themes/tkl/source/fonts/icons.ttf","hash":"2169592997f694ffa05b1d4c23d5a1abf35d3203","modified":1650768698000},{"_id":"themes/tkl/source/fonts/opensans.woff","hash":"43b78d92be59efafc7ada7ee21abd4ba7a65c663","modified":1650768698000},{"_id":"themes/tkl/source/img/close.png","hash":"e52e6a61877efd98ddad9ca31ece27e8ee977327","modified":1650768698000},{"_id":"themes/tkl/source/js/jquery.ajaxchimp.min.js","hash":"9be17785b0d816e1cd6bc45908e1805e0522fe18","modified":1650768698000},{"_id":"themes/tkl/source/img/favicon.ico","hash":"70fbd67d92be00781652fed26bda9af8d931fb0a","modified":1650768698000},{"_id":"themes/tkl/source/js/html5shiv.min.js","hash":"bb51a5f6c394989bb06e4171179354c6d05ec8f8","modified":1650768698000},{"_id":"themes/tkl/source/js/respond.min.js","hash":"b5aba40d65b0d6f85859db47f757ea971a0efd30","modified":1650768698000},{"_id":"themes/tkl/source/js/jquery.flexslider-min.js","hash":"51b3a7d882f438d53dc69ca5289e92254160c09a","modified":1650768698000},{"_id":"themes/tkl/source/highlightjs/arta.css","hash":"08766ac9d70bde457fea9c553140029f57ace65a","modified":1650768698000},{"_id":"themes/tkl/source/js/ziploader.js","hash":"4d487998f85dc6fae6c29c94f0163aa4c309319f","modified":1650768698000},{"_id":"themes/tkl/source/highlightjs/ascetic.css","hash":"dd5e0c6c11bc199884cc5abf7310e79ce8018d0d","modified":1650768698000},{"_id":"themes/tkl/source/js/scripts.js","hash":"9c05b2538f02df0313e6892083d2716d2c258f49","modified":1650768698000},{"_id":"themes/tkl/source/highlightjs/brown_papersq.png","hash":"3a1332ede3a75a3d24f60b6ed69035b72da5e182","modified":1650768698000},{"_id":"themes/tkl/source/highlightjs/docco.css","hash":"70199b44d688d0a22851bd5481260f24160a38ee","modified":1650768698000},{"_id":"themes/tkl/source/highlightjs/brown_paper.css","hash":"2a987d30dd142a5c316ace70e919e3312707ebbd","modified":1650768698000},{"_id":"themes/tkl/source/highlightjs/dark.css","hash":"38045930b1d862bb6e14960e94e63782145a598f","modified":1650768698000},{"_id":"themes/tkl/source/highlightjs/default.css","hash":"108ad8410aa3004eafc452ae60771a2ae24d7988","modified":1650768698000},{"_id":"themes/tkl/source/highlightjs/foundation.css","hash":"308c2e0458fc117b323f7d9ce1644f7b4e52d99e","modified":1650768698000},{"_id":"themes/tkl/source/highlightjs/googlecode.css","hash":"731e74bcdfd1b68aae5b5805540f727c31309ba2","modified":1650768698000},{"_id":"themes/tkl/source/highlightjs/far.css","hash":"8178ac70abe577ae8345f1f6291bf7d489ad384d","modified":1650768698000},{"_id":"themes/tkl/source/highlightjs/idea.css","hash":"fb77c293850c454c1f0c72628c0b301537765ad2","modified":1650768698000},{"_id":"themes/tkl/source/highlightjs/github.css","hash":"53f47e65e6e0e6068baf5c4b638b04d2f4e0b0bc","modified":1650768698000},{"_id":"themes/tkl/source/highlightjs/ir_black.css","hash":"2da52e8562b412039b5816e1a3a2f59e7dff0c27","modified":1650768698000},{"_id":"themes/tkl/source/highlightjs/mono-blue.css","hash":"c143e9d8c62dc71ca39bc0b6c127464ed2396e4f","modified":1650768698000},{"_id":"themes/tkl/source/highlightjs/magula.css","hash":"5666f49986f05fb8956e0c3065a383b252779442","modified":1650768698000},{"_id":"themes/tkl/source/highlightjs/monokai.css","hash":"a0edb8327c191516a04d456db8aae9044055a5cf","modified":1650768698000},{"_id":"themes/tkl/source/highlightjs/obsidian.css","hash":"d6c264e1973beb9f20001b9a4013e9983923b34e","modified":1650768698000},{"_id":"themes/tkl/source/highlightjs/monokai_sublime.css","hash":"6b4716416b1bba643d3a7926221ce6d83a139141","modified":1650768698000},{"_id":"themes/tkl/source/highlightjs/railscasts.css","hash":"aeb6ecd79552b9611d447fe56de5266954ea055c","modified":1650768698000},{"_id":"themes/tkl/source/highlightjs/pojoaque.jpg","hash":"c5fe6533b88b21f8d90d3d03954c6b29baa67791","modified":1650768698000},{"_id":"themes/tkl/source/highlightjs/rainbow.css","hash":"b0e18f0f7fa08d5ad11956e2d9cc5e2ffdd514f3","modified":1650768698000},{"_id":"themes/tkl/source/highlightjs/pojoaque.css","hash":"c9b048dc71c5b45d5cb3daac8f332a7e5d13b20f","modified":1650768698000},{"_id":"themes/tkl/source/highlightjs/school_book.png","hash":"711ec983c874e093bb89eb77afcbdf6741fa61ee","modified":1650768698000},{"_id":"themes/tkl/source/highlightjs/school_book.css","hash":"f257d41cdca2609fa4c664df9cc14b48e2bcb09f","modified":1650768698000},{"_id":"themes/tkl/source/highlightjs/solarized_dark.css","hash":"007f9f1e7addf7e2040734cd1f733d041432c335","modified":1650768698000},{"_id":"themes/tkl/source/highlightjs/tomorrow-night-blue.css","hash":"e2bed22abcdf3f2b8ca3a1a73624751d3edc4e64","modified":1650768698000},{"_id":"themes/tkl/source/highlightjs/sunburst.css","hash":"e72bc116795505c1fcae35bc69045043fc34a243","modified":1650768698000},{"_id":"themes/tkl/source/highlightjs/solarized_light.css","hash":"a85878fd70ecd03c71944df1acbbf320bac7979f","modified":1650768698000},{"_id":"themes/tkl/source/highlightjs/tomorrow-night-bright.css","hash":"afdb004743a8d2b52d38c7a1fce32d631a0f3ded","modified":1650768698000},{"_id":"themes/tkl/source/highlightjs/tomorrow-night-eighties.css","hash":"9603bc778de2dabd0ce1e7ee272a047338a8b99c","modified":1650768698000},{"_id":"themes/tkl/source/highlightjs/tomorrow-night.css","hash":"48cd18ce93daa491d89eb63e5fe3ab640ff56d74","modified":1650768698000},{"_id":"themes/tkl/source/highlightjs/tomorrow.css","hash":"a184e23b28b6a6401ecfc35e0a94de0bada589e4","modified":1650768698000},{"_id":"themes/tkl/source/highlightjs/vs.css","hash":"13e2f7ec2e197d79f4fc36768ea4a0663d41e1c0","modified":1650768698000},{"_id":"themes/tkl/source/highlightjs/xcode.css","hash":"78cb5758ce4085aa51edb6c5beb64d8f4511edd7","modified":1650768698000},{"_id":"themes/tkl/source/highlightjs/zenburn.css","hash":"73dafd21563f5fc3bb74856d4abf97c447a27772","modified":1650768698000},{"_id":"themes/tkl/layout/_partial/post/meta.ejs","hash":"c984cdc774bc884b33c8d87e3b59728cfdee773c","modified":1650768698000},{"_id":"themes/tkl/layout/_partial/post/comments.ejs","hash":"b42d96dc6e14558d31224a10149e2ac104f2da0e","modified":1650768698000},{"_id":"themes/tkl/layout/_partial/post/navigation.ejs","hash":"1dd81ccccc3125d821765cfef1889bd25e85b5d5","modified":1650768698000},{"_id":"themes/tkl/source/css/bootstrap.min.css","hash":"aabbadd6b436fa24c84fd8ca01d433bdab26fba5","modified":1650768698000},{"_id":"themes/tkl/source/img/banner-1033925_640.jpg","hash":"95347171733ca284cb0b8db561eac40d2cdb11a0","modified":1660559438000},{"_id":"themes/tkl/source/css/style.css","hash":"4b2f1e4d1e2ac78454691c7980b6e785979f4218","modified":1660297982000},{"_id":"themes/tkl/source/fonts/icons.svg","hash":"4b8357c608c01f304789e34bfd133081c1fc8b9d","modified":1650768698000},{"_id":"themes/tkl/source/img/1326 - Ring.png","hash":"0f5a80f4e91879d9c851ae0f09b31e8fcaabd471","modified":1660532074000},{"_id":"themes/tkl/source/img/1326 - Ring.ico","hash":"0f5a80f4e91879d9c851ae0f09b31e8fcaabd471","modified":1660649772655},{"_id":"themes/tkl/source/js/jquery-1.11.1.min.js","hash":"d6c1f41972de07b09bfa63d2e50f9ab41ec372bd","modified":1650768698000},{"_id":"themes/tkl/source/js/plugins.min.js","hash":"b9c5dd602b0d25d02ad704eef6e4e4d3b25f78db","modified":1650768698000},{"_id":"public/tags/index.html","hash":"7fec9febd8e1d3738757aa80977463e01a1c8e15","modified":1663643657000},{"_id":"public/categories/index.html","hash":"14751dc849d208a55e11e7a87cf3e2852d2e6600","modified":1663643657000},{"_id":"public/archives/index.html","hash":"c152cf5454fadd501e900365898b98d842872242","modified":1663643657000},{"_id":"public/What-are-the-five-benefits-of-drinking-water-with-thermos-cup/index.html","hash":"20cf13fb74a7e5db84d1f62e30f914b0d5c46f53","modified":1663643657000},{"_id":"public/archives/2022/index.html","hash":"5b57e3b04b7252bfef184c585756c5ad9c2e2e37","modified":1663643657000},{"_id":"public/archives/2022/08/index.html","hash":"0b9aad0132c54eab75203890b628101333d42e2a","modified":1663643657000},{"_id":"public/categories/Thermos-Cup/index.html","hash":"35c4c807f34ca0f41e8dffe257112e0df621cdf8","modified":1663643657000},{"_id":"public/tags/thermos-cup/index.html","hash":"18959ee34db1a8dc32188727a1bc9a7a4f20b868","modified":1663643657000},{"_id":"public/tags/cup-thermos/index.html","hash":"d32881675af751e9c7434611eefb3a1bfed191b1","modified":1663643657000},{"_id":"public/tags/thermos-with-cup/index.html","hash":"4542f205503b274cede9fa2f70b3691cc2d002c6","modified":1663643657000},{"_id":"public/tags/travel-mug/index.html","hash":"a2d72755c7aa870a3f88e8be0aad8bdc7ebfb88d","modified":1663643657000},{"_id":"public/index.html","hash":"db8b933dce905a17a853c4e7cd014e82ab67756b","modified":1663643657000},{"_id":"public/fancybox/fancybox_loading@2x.gif","hash":"273b123496a42ba45c3416adb027cd99745058b0","modified":1660649791083},{"_id":"public/fancybox/fancybox_loading.gif","hash":"1a755fb2599f3a313cc6cfdb14df043f8c14a99c","modified":1660649791083},{"_id":"public/fancybox/fancybox_sprite@2x.png","hash":"30c58913f327e28f466a00f4c1ac8001b560aed8","modified":1660649791083},{"_id":"public/fancybox/fancybox_overlay.png","hash":"b3a4ee645ba494f52840ef8412015ba0f465dbe0","modified":1660649791083},{"_id":"public/fancybox/blank.gif","hash":"2daeaa8b5f19f0bc209d976c02bd6acb51b00b0a","modified":1660649791083},{"_id":"public/fancybox/fancybox_sprite.png","hash":"17df19f97628e77be09c352bf27425faea248251","modified":1660649791083},{"_id":"public/fonts/icons.eot","hash":"e307fc2d61d13bbc3aafc9abd75e727cbebadee1","modified":1660649791083},{"_id":"public/fonts/icons.woff","hash":"af538de6ac19d5da1cada203c7451ce32f5daceb","modified":1660649791083},{"_id":"public/fonts/icons.ttf","hash":"2169592997f694ffa05b1d4c23d5a1abf35d3203","modified":1660649791083},{"_id":"public/fonts/opensans.woff","hash":"43b78d92be59efafc7ada7ee21abd4ba7a65c663","modified":1660649791083},{"_id":"public/img/banner-1033925_640.jpg","hash":"95347171733ca284cb0b8db561eac40d2cdb11a0","modified":1660649791083},{"_id":"public/img/close.png","hash":"e52e6a61877efd98ddad9ca31ece27e8ee977327","modified":1660649791083},{"_id":"public/img/favicon.ico","hash":"70fbd67d92be00781652fed26bda9af8d931fb0a","modified":1660649791083},{"_id":"public/highlightjs/brown_papersq.png","hash":"3a1332ede3a75a3d24f60b6ed69035b72da5e182","modified":1660649791083},{"_id":"public/css/animate.css","hash":"fca75b84887199a0ed8e0f056ff30f5a1302f324","modified":1660649791083},{"_id":"public/css/custom.css","hash":"e87423888bf9a13ee0bc28a5aa725f40f999608a","modified":1660649791083},{"_id":"public/css/screen.css","hash":"a13c2c6fe420f76083df2da6d7b2d765dd8b467e","modified":1660649791083},{"_id":"public/css/ie8.css","hash":"cfdfe07ecc9f3afa5bab47155b49f0924f62d2c2","modified":1660649791083},{"_id":"public/css/flexslider.css","hash":"faebc8c54ca41e3c9936edaffbabbebd512c6d5a","modified":1660649791083},{"_id":"public/css/syntax.css","hash":"d5923a6251a113ac02916bcd1119356bd780d7ef","modified":1660649791083},{"_id":"public/fancybox/jquery.fancybox.css","hash":"5f163444617b6cf267342f06ac166a237bb62df9","modified":1660649791083},{"_id":"public/css/iconList.css","hash":"f78ffffb4be40a6b0eb6ee109c958ccd062d1ae5","modified":1660649791083},{"_id":"public/css/slidebars.min.css","hash":"a802c15d9bf06005b463901be8325d8ce38b5b04","modified":1660649791083},{"_id":"public/js/html5shiv.min.js","hash":"bb51a5f6c394989bb06e4171179354c6d05ec8f8","modified":1660649791083},{"_id":"public/js/jquery.ajaxchimp.min.js","hash":"9be17785b0d816e1cd6bc45908e1805e0522fe18","modified":1660649791083},{"_id":"public/js/scripts.js","hash":"9c05b2538f02df0313e6892083d2716d2c258f49","modified":1660649791083},{"_id":"public/highlightjs/ascetic.css","hash":"ef259aecdc8f1367dcf890d6467369300c4c0d07","modified":1660649791083},{"_id":"public/highlightjs/arta.css","hash":"08766ac9d70bde457fea9c553140029f57ace65a","modified":1660649791083},{"_id":"public/js/respond.min.js","hash":"b5aba40d65b0d6f85859db47f757ea971a0efd30","modified":1660649791083},{"_id":"public/css/all.css","hash":"33cba693ed2007ee5119d0efd97cef9effe4d83d","modified":1660649791083},{"_id":"public/css/animsition.min.css","hash":"59033074f6594a0d87c759e2b8cf9baa3a62ed6a","modified":1660649791083},{"_id":"public/css/bootstrap.min.css","hash":"aabbadd6b436fa24c84fd8ca01d433bdab26fba5","modified":1660649791083},{"_id":"public/js/jquery.flexslider-min.js","hash":"51b3a7d882f438d53dc69ca5289e92254160c09a","modified":1660649791083},{"_id":"public/css/style.css","hash":"4b2f1e4d1e2ac78454691c7980b6e785979f4218","modified":1660649791083},{"_id":"public/fancybox/jquery.fancybox.pack.js","hash":"53360764b429c212f424399384417ccc233bb3be","modified":1660649791083},{"_id":"public/js/ziploader.js","hash":"f0266f9d8f5bd652ab5370fea02ac90401795ee2","modified":1660649791083},{"_id":"public/js/plugins.min.js","hash":"b9c5dd602b0d25d02ad704eef6e4e4d3b25f78db","modified":1660649791083},{"_id":"public/js/jquery-1.11.1.min.js","hash":"d6c1f41972de07b09bfa63d2e50f9ab41ec372bd","modified":1660649791083},{"_id":"public/highlightjs/pojoaque.jpg","hash":"c5fe6533b88b21f8d90d3d03954c6b29baa67791","modified":1660649791083},{"_id":"public/highlightjs/school_book.png","hash":"711ec983c874e093bb89eb77afcbdf6741fa61ee","modified":1660649791083},{"_id":"public/fonts/icons.svg","hash":"4b8357c608c01f304789e34bfd133081c1fc8b9d","modified":1660649791083},{"_id":"public/img/1326 - Ring.ico","hash":"0f5a80f4e91879d9c851ae0f09b31e8fcaabd471","modified":1660649791083},{"_id":"public/img/1326 - Ring.png","hash":"0f5a80f4e91879d9c851ae0f09b31e8fcaabd471","modified":1660649791083},{"_id":"public/highlightjs/default.css","hash":"108ad8410aa3004eafc452ae60771a2ae24d7988","modified":1660649791083},{"_id":"public/highlightjs/brown_paper.css","hash":"2a987d30dd142a5c316ace70e919e3312707ebbd","modified":1660649791083},{"_id":"public/highlightjs/dark.css","hash":"2c2b4eb2562d812d95a26da0ffae51371b383713","modified":1660649791083},{"_id":"public/highlightjs/far.css","hash":"8178ac70abe577ae8345f1f6291bf7d489ad384d","modified":1660649791083},{"_id":"public/highlightjs/foundation.css","hash":"308c2e0458fc117b323f7d9ce1644f7b4e52d99e","modified":1660649791083},{"_id":"public/highlightjs/docco.css","hash":"70199b44d688d0a22851bd5481260f24160a38ee","modified":1660649791083},{"_id":"public/highlightjs/googlecode.css","hash":"731e74bcdfd1b68aae5b5805540f727c31309ba2","modified":1660649791083},{"_id":"public/highlightjs/ir_black.css","hash":"2da52e8562b412039b5816e1a3a2f59e7dff0c27","modified":1660649791083},{"_id":"public/highlightjs/github.css","hash":"53f47e65e6e0e6068baf5c4b638b04d2f4e0b0bc","modified":1660649791083},{"_id":"public/highlightjs/idea.css","hash":"fb77c293850c454c1f0c72628c0b301537765ad2","modified":1660649791083},{"_id":"public/highlightjs/magula.css","hash":"9c53982a77259331c1dc3b24ef744dd76b3fe643","modified":1660649791083},{"_id":"public/highlightjs/mono-blue.css","hash":"c143e9d8c62dc71ca39bc0b6c127464ed2396e4f","modified":1660649791083},{"_id":"public/highlightjs/monokai.css","hash":"a0edb8327c191516a04d456db8aae9044055a5cf","modified":1660649791083},{"_id":"public/highlightjs/obsidian.css","hash":"d6c264e1973beb9f20001b9a4013e9983923b34e","modified":1660649791083},{"_id":"public/highlightjs/monokai_sublime.css","hash":"6b4716416b1bba643d3a7926221ce6d83a139141","modified":1660649791083},{"_id":"public/highlightjs/rainbow.css","hash":"b0e18f0f7fa08d5ad11956e2d9cc5e2ffdd514f3","modified":1660649791083},{"_id":"public/highlightjs/pojoaque.css","hash":"c9b048dc71c5b45d5cb3daac8f332a7e5d13b20f","modified":1660649791083},{"_id":"public/highlightjs/railscasts.css","hash":"aeb6ecd79552b9611d447fe56de5266954ea055c","modified":1660649791083},{"_id":"public/highlightjs/school_book.css","hash":"f257d41cdca2609fa4c664df9cc14b48e2bcb09f","modified":1660649791083},{"_id":"public/highlightjs/tomorrow-night-blue.css","hash":"e2bed22abcdf3f2b8ca3a1a73624751d3edc4e64","modified":1660649791083},{"_id":"public/highlightjs/solarized_dark.css","hash":"007f9f1e7addf7e2040734cd1f733d041432c335","modified":1660649791083},{"_id":"public/highlightjs/solarized_light.css","hash":"a85878fd70ecd03c71944df1acbbf320bac7979f","modified":1660649791083},{"_id":"public/highlightjs/tomorrow-night-bright.css","hash":"afdb004743a8d2b52d38c7a1fce32d631a0f3ded","modified":1660649791083},{"_id":"public/highlightjs/sunburst.css","hash":"e72bc116795505c1fcae35bc69045043fc34a243","modified":1660649791083},{"_id":"public/highlightjs/tomorrow-night.css","hash":"48cd18ce93daa491d89eb63e5fe3ab640ff56d74","modified":1660649791083},{"_id":"public/highlightjs/tomorrow-night-eighties.css","hash":"9603bc778de2dabd0ce1e7ee272a047338a8b99c","modified":1660649791083},{"_id":"public/highlightjs/vs.css","hash":"13e2f7ec2e197d79f4fc36768ea4a0663d41e1c0","modified":1660649791083},{"_id":"public/highlightjs/tomorrow.css","hash":"a184e23b28b6a6401ecfc35e0a94de0bada589e4","modified":1660649791083},{"_id":"public/highlightjs/zenburn.css","hash":"73dafd21563f5fc3bb74856d4abf97c447a27772","modified":1660649791083},{"_id":"public/highlightjs/xcode.css","hash":"78cb5758ce4085aa51edb6c5beb64d8f4511edd7","modified":1660649791083}],"Category":[{"name":"Thermos Cup","_id":"cl6w40by20003pcv54s1b1ico"}],"Data":[],"Page":[{"title":"tags","date":"2022-08-16T11:36:15.000Z","type":"tags","layout":"tags","_content":"","source":"tags/index.md","raw":"---\ntitle: tags\ndate: 2022-08-16 19:36:15\ntype: \"tags\"\nlayout: \"tags\"\n---\n","updated":"2022-08-16T11:36:15.503Z","path":"tags/index.html","comments":1,"_id":"cl6w40bxo0000pcv5cgcp7yp2","content":"","site":{"data":{}},"excerpt":"","more":""},{"title":"categories","date":"2022-08-16T11:36:14.000Z","type":"categories","layout":"categories","_content":"","source":"categories/index.md","raw":"---\ntitle: categories\ndate: 2022-08-16 19:36:14\ntype: \"categories\"\nlayout: \"categories\"\n---\n","updated":"2022-08-16T11:36:14.106Z","path":"categories/index.html","comments":1,"_id":"cl6w40bxr0001pcv59iij67fy","content":"","site":{"data":{}},"excerpt":"","more":""}],"Post":[{"title":"What are the five benefits of drinking water with thermos cup","date":"2022-08-16T11:36:29.000Z","_content":"\n\n#  What are the five benefits of drinking water with thermos cup?\n\n1. If you drink 8-10 glasses of water per day, you can enjoy the health benefits of drinking water. When you drink water from a thermos cup, you'll stay hydrated longer because the temperature is regulated and it's insulated.\n\n2. Drinking hot water has multiple benefits. It boosts your metabolism and helps to cleanse your system by promoting urination.\n\n3. A thermos cup will keep your coffee or tea warm for hours, allowing you to enjoy a hot beverage whenever you want.\n\n4. Most thermos cups are made with stainless steel or other high-quality materials that make them durable and BPA-free.\n\n5. They're easy to use and easy to clean, making them a convenient option for on-the-go drinkers.\n\n#  How can drinking water with thermos cup improve your health?\n\nIf you’re looking for a way to improve your health, drinking water with a thermos cup may be the answer. Drinking plenty of water is essential for good health, and using a thermos cup to keep your water warm can make it more pleasant to drink. Warm water is also thought to be more beneficial than cold water. Here are four ways that drinking water with a thermos cup can benefit your health:\n\n1.Drinking warm water helps digestion.\n\nThe warmth of the water stimulates digestive juices and helps them flow more freely. This can help improve digestion and make it easier for your body to absorb nutrients from food.\n\n2.Warming up the body warms up the immune system.\n\nDrinking warm fluids, such as tea or soup, when you’re feeling cold or sick can help “warm up” your immune system and make you feel better faster. Warmed-up blood vessels promote blood circulation, allowing white blood cells to circulate better and fight infection more effectively.\n\n3.Warm liquids relieve congestion and help clear sinuses.\n\nWhen you’re dealing with a cold or the flu, drinking hot liquids can help loosen secretions and mucus in the respiratory tract, which can then be expelled more easily. Hot liquids also help soothe inflamed nasal passages.\n\n4.Warm liquids are soothing and relaxing.\n\nDrinking something warm before bedtime can promote relaxation and help you fall asleep faster. Warm liquids are also known to be soothing for the stomach and can help relieve pain or discomfort in that area\n\n#  What are some of the potential risks associated with drinking water from a thermos cup?\n\nWhen it comes to drinking water, there are a number of potential risks associated with using a thermos cup. One of the most common risks is that the water may not be safe to drink. This is especially true if the thermos has been used to store food or other liquids that are not safe to drink. Another common risk is that the water may not be hot enough to kill any bacteria that may be present in the water. This can lead to stomach upset or other health problems. Another potential risk is that the thermos cup may not keep the water warm for very long. This can cause the water to become cold and uncomfortable to drink.\n\n#  What should you do if you experience any negative side effects after drinking water from a thermos cup?\n\nIf you experience any negative side effects after drinking water from a thermos cup, such as nausea or vomiting, you should seek medical attention.\n\n#  How can you make sure that you're getting the most out of your thermos cup water drinking experience?\n\nThere are a few things that you can do to make sure that you're getting the most out of your thermos cup water drinking experience. First, make sure that you're cleaning your thermos regularly. Bacteria can build up over time, and this can make your water taste bad. Second, try not to fill your thermos all the way to the top. This will help to ensure that your water stays cold for longer. Finally, drink your water regularly! If you let it sit in the thermos for too long, it will start to taste stale.","source":"_posts/What-are-the-five-benefits-of-drinking-water-with-thermos-cup.md","raw":"---\ntitle: What are the five benefits of drinking water with thermos cup\ndate: 2022-08-16 19:36:29\ncategories:\n- Thermos Cup\ntags:\n- thermos cup\n- thermos with cup\n- cup thermos\n- travel mug\n---\n\n\n#  What are the five benefits of drinking water with thermos cup?\n\n1. If you drink 8-10 glasses of water per day, you can enjoy the health benefits of drinking water. When you drink water from a thermos cup, you'll stay hydrated longer because the temperature is regulated and it's insulated.\n\n2. Drinking hot water has multiple benefits. It boosts your metabolism and helps to cleanse your system by promoting urination.\n\n3. A thermos cup will keep your coffee or tea warm for hours, allowing you to enjoy a hot beverage whenever you want.\n\n4. Most thermos cups are made with stainless steel or other high-quality materials that make them durable and BPA-free.\n\n5. They're easy to use and easy to clean, making them a convenient option for on-the-go drinkers.\n\n#  How can drinking water with thermos cup improve your health?\n\nIf you’re looking for a way to improve your health, drinking water with a thermos cup may be the answer. Drinking plenty of water is essential for good health, and using a thermos cup to keep your water warm can make it more pleasant to drink. Warm water is also thought to be more beneficial than cold water. Here are four ways that drinking water with a thermos cup can benefit your health:\n\n1.Drinking warm water helps digestion.\n\nThe warmth of the water stimulates digestive juices and helps them flow more freely. This can help improve digestion and make it easier for your body to absorb nutrients from food.\n\n2.Warming up the body warms up the immune system.\n\nDrinking warm fluids, such as tea or soup, when you’re feeling cold or sick can help “warm up” your immune system and make you feel better faster. Warmed-up blood vessels promote blood circulation, allowing white blood cells to circulate better and fight infection more effectively.\n\n3.Warm liquids relieve congestion and help clear sinuses.\n\nWhen you’re dealing with a cold or the flu, drinking hot liquids can help loosen secretions and mucus in the respiratory tract, which can then be expelled more easily. Hot liquids also help soothe inflamed nasal passages.\n\n4.Warm liquids are soothing and relaxing.\n\nDrinking something warm before bedtime can promote relaxation and help you fall asleep faster. Warm liquids are also known to be soothing for the stomach and can help relieve pain or discomfort in that area\n\n#  What are some of the potential risks associated with drinking water from a thermos cup?\n\nWhen it comes to drinking water, there are a number of potential risks associated with using a thermos cup. One of the most common risks is that the water may not be safe to drink. This is especially true if the thermos has been used to store food or other liquids that are not safe to drink. Another common risk is that the water may not be hot enough to kill any bacteria that may be present in the water. This can lead to stomach upset or other health problems. Another potential risk is that the thermos cup may not keep the water warm for very long. This can cause the water to become cold and uncomfortable to drink.\n\n#  What should you do if you experience any negative side effects after drinking water from a thermos cup?\n\nIf you experience any negative side effects after drinking water from a thermos cup, such as nausea or vomiting, you should seek medical attention.\n\n#  How can you make sure that you're getting the most out of your thermos cup water drinking experience?\n\nThere are a few things that you can do to make sure that you're getting the most out of your thermos cup water drinking experience. First, make sure that you're cleaning your thermos regularly. Bacteria can build up over time, and this can make your water taste bad. Second, try not to fill your thermos all the way to the top. This will help to ensure that your water stays cold for longer. Finally, drink your water regularly! If you let it sit in the thermos for too long, it will start to taste stale.","slug":"What-are-the-five-benefits-of-drinking-water-with-thermos-cup","published":1,"updated":"2022-08-16T11:36:29.881Z","comments":1,"layout":"post","photos":[],"link":"","_id":"cl6w40bxz0002pcv50ih7fi73","content":"<h1 id=\"What-are-the-five-benefits-of-drinking-water-with-thermos-cup\"><a href=\"#What-are-the-five-benefits-of-drinking-water-with-thermos-cup\" class=\"headerlink\" title=\"What are the five benefits of drinking water with thermos cup?\"></a>What are the five benefits of drinking water with thermos cup?</h1><ol>\n<li><p>If you drink 8-10 glasses of water per day, you can enjoy the health benefits of drinking water. When you drink water from a thermos cup, you’ll stay hydrated longer because the temperature is regulated and it’s insulated.</p>\n</li>\n<li><p>Drinking hot water has multiple benefits. It boosts your metabolism and helps to cleanse your system by promoting urination.</p>\n</li>\n<li><p>A thermos cup will keep your coffee or tea warm for hours, allowing you to enjoy a hot beverage whenever you want.</p>\n</li>\n<li><p>Most thermos cups are made with stainless steel or other high-quality materials that make them durable and BPA-free.</p>\n</li>\n<li><p>They’re easy to use and easy to clean, making them a convenient option for on-the-go drinkers.</p>\n</li>\n</ol>\n<h1 id=\"How-can-drinking-water-with-thermos-cup-improve-your-health\"><a href=\"#How-can-drinking-water-with-thermos-cup-improve-your-health\" class=\"headerlink\" title=\"How can drinking water with thermos cup improve your health?\"></a>How can drinking water with thermos cup improve your health?</h1><p>If you’re looking for a way to improve your health, drinking water with a thermos cup may be the answer. Drinking plenty of water is essential for good health, and using a thermos cup to keep your water warm can make it more pleasant to drink. Warm water is also thought to be more beneficial than cold water. Here are four ways that drinking water with a thermos cup can benefit your health:</p>\n<p>1.Drinking warm water helps digestion.</p>\n<p>The warmth of the water stimulates digestive juices and helps them flow more freely. This can help improve digestion and make it easier for your body to absorb nutrients from food.</p>\n<p>2.Warming up the body warms up the immune system.</p>\n<p>Drinking warm fluids, such as tea or soup, when you’re feeling cold or sick can help “warm up” your immune system and make you feel better faster. Warmed-up blood vessels promote blood circulation, allowing white blood cells to circulate better and fight infection more effectively.</p>\n<p>3.Warm liquids relieve congestion and help clear sinuses.</p>\n<p>When you’re dealing with a cold or the flu, drinking hot liquids can help loosen secretions and mucus in the respiratory tract, which can then be expelled more easily. Hot liquids also help soothe inflamed nasal passages.</p>\n<p>4.Warm liquids are soothing and relaxing.</p>\n<p>Drinking something warm before bedtime can promote relaxation and help you fall asleep faster. Warm liquids are also known to be soothing for the stomach and can help relieve pain or discomfort in that area</p>\n<h1 id=\"What-are-some-of-the-potential-risks-associated-with-drinking-water-from-a-thermos-cup\"><a href=\"#What-are-some-of-the-potential-risks-associated-with-drinking-water-from-a-thermos-cup\" class=\"headerlink\" title=\"What are some of the potential risks associated with drinking water from a thermos cup?\"></a>What are some of the potential risks associated with drinking water from a thermos cup?</h1><p>When it comes to drinking water, there are a number of potential risks associated with using a thermos cup. One of the most common risks is that the water may not be safe to drink. This is especially true if the thermos has been used to store food or other liquids that are not safe to drink. Another common risk is that the water may not be hot enough to kill any bacteria that may be present in the water. This can lead to stomach upset or other health problems. Another potential risk is that the thermos cup may not keep the water warm for very long. This can cause the water to become cold and uncomfortable to drink.</p>\n<h1 id=\"What-should-you-do-if-you-experience-any-negative-side-effects-after-drinking-water-from-a-thermos-cup\"><a href=\"#What-should-you-do-if-you-experience-any-negative-side-effects-after-drinking-water-from-a-thermos-cup\" class=\"headerlink\" title=\"What should you do if you experience any negative side effects after drinking water from a thermos cup?\"></a>What should you do if you experience any negative side effects after drinking water from a thermos cup?</h1><p>If you experience any negative side effects after drinking water from a thermos cup, such as nausea or vomiting, you should seek medical attention.</p>\n<h1 id=\"How-can-you-make-sure-that-you’re-getting-the-most-out-of-your-thermos-cup-water-drinking-experience\"><a href=\"#How-can-you-make-sure-that-you’re-getting-the-most-out-of-your-thermos-cup-water-drinking-experience\" class=\"headerlink\" title=\"How can you make sure that you’re getting the most out of your thermos cup water drinking experience?\"></a>How can you make sure that you’re getting the most out of your thermos cup water drinking experience?</h1><p>There are a few things that you can do to make sure that you’re getting the most out of your thermos cup water drinking experience. First, make sure that you’re cleaning your thermos regularly. Bacteria can build up over time, and this can make your water taste bad. Second, try not to fill your thermos all the way to the top. This will help to ensure that your water stays cold for longer. Finally, drink your water regularly! If you let it sit in the thermos for too long, it will start to taste stale.</p>\n","site":{"data":{}},"excerpt":"","more":"<h1 id=\"What-are-the-five-benefits-of-drinking-water-with-thermos-cup\"><a href=\"#What-are-the-five-benefits-of-drinking-water-with-thermos-cup\" class=\"headerlink\" title=\"What are the five benefits of drinking water with thermos cup?\"></a>What are the five benefits of drinking water with thermos cup?</h1><ol>\n<li><p>If you drink 8-10 glasses of water per day, you can enjoy the health benefits of drinking water. When you drink water from a thermos cup, you’ll stay hydrated longer because the temperature is regulated and it’s insulated.</p>\n</li>\n<li><p>Drinking hot water has multiple benefits. It boosts your metabolism and helps to cleanse your system by promoting urination.</p>\n</li>\n<li><p>A thermos cup will keep your coffee or tea warm for hours, allowing you to enjoy a hot beverage whenever you want.</p>\n</li>\n<li><p>Most thermos cups are made with stainless steel or other high-quality materials that make them durable and BPA-free.</p>\n</li>\n<li><p>They’re easy to use and easy to clean, making them a convenient option for on-the-go drinkers.</p>\n</li>\n</ol>\n<h1 id=\"How-can-drinking-water-with-thermos-cup-improve-your-health\"><a href=\"#How-can-drinking-water-with-thermos-cup-improve-your-health\" class=\"headerlink\" title=\"How can drinking water with thermos cup improve your health?\"></a>How can drinking water with thermos cup improve your health?</h1><p>If you’re looking for a way to improve your health, drinking water with a thermos cup may be the answer. Drinking plenty of water is essential for good health, and using a thermos cup to keep your water warm can make it more pleasant to drink. Warm water is also thought to be more beneficial than cold water. Here are four ways that drinking water with a thermos cup can benefit your health:</p>\n<p>1.Drinking warm water helps digestion.</p>\n<p>The warmth of the water stimulates digestive juices and helps them flow more freely. This can help improve digestion and make it easier for your body to absorb nutrients from food.</p>\n<p>2.Warming up the body warms up the immune system.</p>\n<p>Drinking warm fluids, such as tea or soup, when you’re feeling cold or sick can help “warm up” your immune system and make you feel better faster. Warmed-up blood vessels promote blood circulation, allowing white blood cells to circulate better and fight infection more effectively.</p>\n<p>3.Warm liquids relieve congestion and help clear sinuses.</p>\n<p>When you’re dealing with a cold or the flu, drinking hot liquids can help loosen secretions and mucus in the respiratory tract, which can then be expelled more easily. Hot liquids also help soothe inflamed nasal passages.</p>\n<p>4.Warm liquids are soothing and relaxing.</p>\n<p>Drinking something warm before bedtime can promote relaxation and help you fall asleep faster. Warm liquids are also known to be soothing for the stomach and can help relieve pain or discomfort in that area</p>\n<h1 id=\"What-are-some-of-the-potential-risks-associated-with-drinking-water-from-a-thermos-cup\"><a href=\"#What-are-some-of-the-potential-risks-associated-with-drinking-water-from-a-thermos-cup\" class=\"headerlink\" title=\"What are some of the potential risks associated with drinking water from a thermos cup?\"></a>What are some of the potential risks associated with drinking water from a thermos cup?</h1><p>When it comes to drinking water, there are a number of potential risks associated with using a thermos cup. One of the most common risks is that the water may not be safe to drink. This is especially true if the thermos has been used to store food or other liquids that are not safe to drink. Another common risk is that the water may not be hot enough to kill any bacteria that may be present in the water. This can lead to stomach upset or other health problems. Another potential risk is that the thermos cup may not keep the water warm for very long. This can cause the water to become cold and uncomfortable to drink.</p>\n<h1 id=\"What-should-you-do-if-you-experience-any-negative-side-effects-after-drinking-water-from-a-thermos-cup\"><a href=\"#What-should-you-do-if-you-experience-any-negative-side-effects-after-drinking-water-from-a-thermos-cup\" class=\"headerlink\" title=\"What should you do if you experience any negative side effects after drinking water from a thermos cup?\"></a>What should you do if you experience any negative side effects after drinking water from a thermos cup?</h1><p>If you experience any negative side effects after drinking water from a thermos cup, such as nausea or vomiting, you should seek medical attention.</p>\n<h1 id=\"How-can-you-make-sure-that-you’re-getting-the-most-out-of-your-thermos-cup-water-drinking-experience\"><a href=\"#How-can-you-make-sure-that-you’re-getting-the-most-out-of-your-thermos-cup-water-drinking-experience\" class=\"headerlink\" title=\"How can you make sure that you’re getting the most out of your thermos cup water drinking experience?\"></a>How can you make sure that you’re getting the most out of your thermos cup water drinking experience?</h1><p>There are a few things that you can do to make sure that you’re getting the most out of your thermos cup water drinking experience. First, make sure that you’re cleaning your thermos regularly. Bacteria can build up over time, and this can make your water taste bad. Second, try not to fill your thermos all the way to the top. This will help to ensure that your water stays cold for longer. Finally, drink your water regularly! If you let it sit in the thermos for too long, it will start to taste stale.</p>\n"}],"PostAsset":[],"PostCategory":[{"post_id":"cl6w40bxz0002pcv50ih7fi73","category_id":"cl6w40by20003pcv54s1b1ico","_id":"cl6w40by50006pcv566ez3nl8"}],"PostTag":[{"post_id":"cl6w40bxz0002pcv50ih7fi73","tag_id":"cl6w40by40004pcv5a6t5axd1","_id":"cl6w40by60009pcv55ymp8yj3"},{"post_id":"cl6w40bxz0002pcv50ih7fi73","tag_id":"cl6w40by50005pcv5glnuc74o","_id":"cl6w40by6000apcv5cs7q6t2w"},{"post_id":"cl6w40bxz0002pcv50ih7fi73","tag_id":"cl6w40by50007pcv512zmc95r","_id":"cl6w40by6000bpcv5hpvfgfmz"},{"post_id":"cl6w40bxz0002pcv50ih7fi73","tag_id":"cl6w40by60008pcv5gze2cvko","_id":"cl6w40by7000cpcv59t950nps"}],"Tag":[{"name":"thermos cup","_id":"cl6w40by40004pcv5a6t5axd1"},{"name":"thermos with cup","_id":"cl6w40by50005pcv5glnuc74o"},{"name":"cup thermos","_id":"cl6w40by50007pcv512zmc95r"},{"name":"travel mug","_id":"cl6w40by60008pcv5gze2cvko"}]}}